odoo8_addon_crm_action-8.0.1.2.0.99.dev41-py3.8-nspkg.pth
odoo_addons/crm_action/README.rst
odoo_addons/crm_action/__init__.py
odoo_addons/crm_action/__openerp__.py
odoo_addons/crm_action/data/email_reminder.xml
odoo_addons/crm_action/demo/demo.xml
odoo_addons/crm_action/i18n/am.po
odoo_addons/crm_action/i18n/ar.po
odoo_addons/crm_action/i18n/bg.po
odoo_addons/crm_action/i18n/bs.po
odoo_addons/crm_action/i18n/ca.po
odoo_addons/crm_action/i18n/ca_ES.po
odoo_addons/crm_action/i18n/crm_action.pot
odoo_addons/crm_action/i18n/cs.po
odoo_addons/crm_action/i18n/da.po
odoo_addons/crm_action/i18n/de.po
odoo_addons/crm_action/i18n/el_GR.po
odoo_addons/crm_action/i18n/en_GB.po
odoo_addons/crm_action/i18n/es.po
odoo_addons/crm_action/i18n/es_AR.po
odoo_addons/crm_action/i18n/es_CL.po
odoo_addons/crm_action/i18n/es_CO.po
odoo_addons/crm_action/i18n/es_CR.po
odoo_addons/crm_action/i18n/es_DO.po
odoo_addons/crm_action/i18n/es_EC.po
odoo_addons/crm_action/i18n/es_ES.po
odoo_addons/crm_action/i18n/es_MX.po
odoo_addons/crm_action/i18n/es_PE.po
odoo_addons/crm_action/i18n/es_PY.po
odoo_addons/crm_action/i18n/es_VE.po
odoo_addons/crm_action/i18n/et.po
odoo_addons/crm_action/i18n/eu.po
odoo_addons/crm_action/i18n/eu_ES.po
odoo_addons/crm_action/i18n/fa.po
odoo_addons/crm_action/i18n/fi.po
odoo_addons/crm_action/i18n/fr.po
odoo_addons/crm_action/i18n/fr_CA.po
odoo_addons/crm_action/i18n/fr_CH.po
odoo_addons/crm_action/i18n/fr_FR.po
odoo_addons/crm_action/i18n/gl.po
odoo_addons/crm_action/i18n/gl_ES.po
odoo_addons/crm_action/i18n/he.po
odoo_addons/crm_action/i18n/hr.po
odoo_addons/crm_action/i18n/hr_HR.po
odoo_addons/crm_action/i18n/hu.po
odoo_addons/crm_action/i18n/id.po
odoo_addons/crm_action/i18n/it.po
odoo_addons/crm_action/i18n/ja.po
odoo_addons/crm_action/i18n/ko.po
odoo_addons/crm_action/i18n/lt.po
odoo_addons/crm_action/i18n/lt_LT.po
odoo_addons/crm_action/i18n/lv.po
odoo_addons/crm_action/i18n/mk.po
odoo_addons/crm_action/i18n/mn.po
odoo_addons/crm_action/i18n/nb.po
odoo8_addon_crm_action-8.0.1.2.0.99.dev41.dist-info/METADATA
odoo8_addon_crm_action-8.0.1.2.0.99.dev41.dist-info/WHEEL
odoo8_addon_crm_action-8.0.1.2.0.99.dev41.dist-info/namespace_packages.txt
odoo8_addon_crm_action-8.0.1.2.0.99.dev41.dist-info/top_level.txt
odoo8_addon_crm_action-8.0.1.2.0.99.dev41.dist-info/RECORD
